odoo/addons/account_cutoff_accrual_picking/README.rst
odoo/addons/account_cutoff_accrual_picking/__init__.py
odoo/addons/account_cutoff_accrual_picking/__manifest__.py
odoo/addons/account_cutoff_accrual_picking/i18n/account_cutoff_accrual_picking.pot
odoo/addons/account_cutoff_accrual_picking/i18n/de.po
odoo/addons/account_cutoff_accrual_picking/i18n/fr_BE.po
odoo/addons/account_cutoff_accrual_picking/i18n/fr_FR.po
odoo/addons/account_cutoff_accrual_picking/i18n/it.po
odoo/addons/account_cutoff_accrual_picking/images/accrued_expense_done.jpg
odoo/addons/account_cutoff_accrual_picking/images/accrued_expense_draft.jpg
odoo/addons/account_cutoff_accrual_picking/images/accrued_expense_journal_entry.jpg
odoo/addons/account_cutoff_accrual_picking/models/__init__.py
odoo/addons/account_cutoff_accrual_picking/models/account_cutoff.py
odoo/addons/account_cutoff_accrual_picking/models/res_company.py
odoo/addons/account_cutoff_accrual_picking/readme/CONFIGURE.rst
odoo/addons/account_cutoff_accrual_picking/readme/CONTRIBUTORS.rst
odoo/addons/account_cutoff_accrual_picking/readme/DESCRIPTION.rst
odoo/addons/account_cutoff_accrual_picking/static/description/icon.png
odoo/addons/account_cutoff_accrual_picking/static/description/index.html
odoo/addons/account_cutoff_accrual_picking/static/src/img/icon.png
odoo/addons/account_cutoff_accrual_picking/views/account_cutoff.xml
odoo/addons/account_cutoff_accrual_picking/views/res_config_settings.xml
odoo/addons/account_cutoff_accrual_picking/wizards/__init__.py
odoo/addons/account_cutoff_accrual_picking/wizards/res_config_settings.py
odoo14_addon_account_cutoff_accrual_picking-14.0.2.0.1.dist-info/METADATA
odoo14_addon_account_cutoff_accrual_picking-14.0.2.0.1.dist-info/WHEEL
odoo14_addon_account_cutoff_accrual_picking-14.0.2.0.1.dist-info/top_level.txt
odoo14_addon_account_cutoff_accrual_picking-14.0.2.0.1.dist-info/RECORD
